{
    "Routes": [
        {
            "DownstreamPathTemplate": "/api/v1/auth/{everything}",
            "DownstreamScheme": "http",
            "DownstreamHostAndPorts": [
                {
                    "Host": "localhost",
                    "Port": 5114
                }
            ],
            "UpstreamPathTemplate": "/v1/auth/{everything}",
            "UpstreamHttpMethod": [ "POST", "GET" ]
        },
        {
            "DownstreamPathTemplate": "/api/v1/hotel/{everything}",
            "DownstreamScheme": "http",
            "DownstreamHostAndPorts": [
                {
                    "Host": "localhost",
                    "Port": 5264
                }
            ],
            "UpstreamPathTemplate": "/v1/hotel/{everything}",
            "UpstreamHttpMethod": [ "POST", "GET", "PUT" ]
        }
    ],
    "GlobalConfiguration": {
        "BaseUrl": "http://localhost:5092"
    }
}
